pyhandytools/__init__.py
pyhandytools/calc.py
pyhandytools/cleaner.py
pyhandytools/crypto.py
pyhandytools/env.py
pyhandytools/file.py
pyhandytools/logger.py
pyhandytools/req.py
pyhandytools-2.0.1.dist-info/LICENSE
pyhandytools-2.0.1.dist-info/METADATA
pyhandytools-2.0.1.dist-info/WHEEL
pyhandytools-2.0.1.dist-info/top_level.txt
pyhandytools-2.0.1.dist-info/RECORD
